dataanalysts/__init__.py
dataanalysts/cleaner.py
dataanalysts/exceptions.py
dataanalysts/load.py
dataanalysts/summary.py
dataanalysts/transformer.py
dataanalysts/visualizer.py
dataanalysts-2.1.0.dist-info/LICENSE
dataanalysts-2.1.0.dist-info/METADATA
dataanalysts-2.1.0.dist-info/WHEEL
dataanalysts-2.1.0.dist-info/top_level.txt
dataanalysts-2.1.0.dist-info/RECORD
