Metadata-Version: 2.1
Name: dataanalysts
Version: 2.1.0
Summary: A powerful Python library designed to simplify data analysis by providing one-line solutions for cleaning, transformation, and visualization. Eliminate boilerplate code with intuitive, feature-rich functions tailored for analysts, researchers, and developers. Streamline workflows with advanced preprocessing and insightful visualizations, all in a single, user-friendly package.
Home-page: https://github.com/yourusername/dataanalysts
Author: Venkata Govind Neelapu
Author-email: venkatagovindneelapu@gmail.com
License: MIT
Classifier: Programming Language :: Python :: 3
Classifier: License :: OSI Approved :: MIT License
Classifier: Operating System :: OS Independent
Requires-Python: >=3.8
License-File: LICENSE
Requires-Dist: pandas
Requires-Dist: numpy
Requires-Dist: matplotlib
Requires-Dist: scikit-learn
Requires-Dist: seaborn
